[{
    "SIDS":
    {
        "color":"#AEFFEC",
        "value":15000,
        "order":1
    },
    "LDCS":
    {
        "color":"#55ECD1",
        "value":10000,
        "order":2,
        "overlap":3000
    },
    "LLDCS":
    {
        "color":"#00D2E0",
        "value":50000,
        "order":3,
        "overlap":5000
    },
    "Other":
    {
        "color":"#03C38A",
        "value":20000,
        "order":4
    }
},
{
    "GEN1":
    {
        "color":"#AEFFEC",
        "value":15000000,
        "order":1
    },
    "GEN2":
    {
        "color":"#55ECD1",
        "value":1000000,
        "order":2
    },
    "GEN3":
    {
        "color":"#00D2E0",
        "value":0,
        "order":3
    },
    "GEN4":
    {
        "color":"#03C38A",
        "value":3000000,
        "order":4
    }
}
]